dbst/__init__.py
dbst/alerts.py
dbst/app.py
dbst/db.py
dbst/monitoring.py
dbst/patterns.py
dbst/schema.py
dbst-0.1.1.dist-info/LICENSE
dbst-0.1.1.dist-info/METADATA
dbst-0.1.1.dist-info/WHEEL
dbst-0.1.1.dist-info/entry_points.txt
dbst-0.1.1.dist-info/RECORD
