Metadata-Version: 2.1
Name: dbst
Version: 0.1.1
Summary: DataBase Staleness Detection
Home-page: https://github.com/namilinklabs/dbst
License: MIT
Author: Namilink
Author-email: dbst@namilink.com
Requires-Python: >=3.10,<4.0
Classifier: Development Status :: 3 - Alpha
Classifier: Intended Audience :: Developers
Classifier: License :: OSI Approved :: MIT License
Classifier: Operating System :: OS Independent
Classifier: Programming Language :: Python :: 3
Classifier: Programming Language :: Python :: 3.10
Classifier: Programming Language :: Python :: 3.11
Classifier: Programming Language :: Python :: 3.12
Classifier: Programming Language :: Python :: 3.13
Classifier: Programming Language :: Python :: 3.8
Classifier: Programming Language :: Python :: 3.9
Classifier: Topic :: Software Development :: Quality Assurance
Project-URL: Documentation, https://github.com/namilinklabs/dbst
Project-URL: Repository, https://github.com/namilinklabs/dbst
